Metadata-Version: 1.0
Name: ipbook
Version: 0.1.2
Summary: Allows you to save IP addresses so that they are accessible in the command line
Home-page: UNKNOWN
Author: Brandon J. Yi
Author-email: bypie966@gmail.com
License: UNKNOWN
Platform: UNKNOWN
